golem_faucet/__init__.py
golem_faucet-0.1.1.dist-info/METADATA
golem_faucet-0.1.1.dist-info/WHEEL
golem_faucet-0.1.1.dist-info/RECORD
